schemahound/__init__.py
schemahound/__main__.py
schemahound/core.py
schemahound/cli/__init__.py
schemahound/cli/main.py
schemahound-0.1.4.dist-info/licenses/LICENSE
schemahound-0.1.4.dist-info/METADATA
schemahound-0.1.4.dist-info/WHEEL
schemahound-0.1.4.dist-info/entry_points.txt
schemahound-0.1.4.dist-info/top_level.txt
schemahound-0.1.4.dist-info/RECORD
